viyapy/__init__.py
viyapy/viya_utils.py
viyapy-1.0.0.dist-info/LICENSE
viyapy-1.0.0.dist-info/METADATA
viyapy-1.0.0.dist-info/WHEEL
viyapy-1.0.0.dist-info/top_level.txt
viyapy-1.0.0.dist-info/RECORD
