Metadata-Version: 2.1
Name: viyapy
Version: 1.0.0
Summary: Utilities for SAS Viya
Home-page: https://github.com/Shai-Alit/viyapy
Author: Sean T Ford
Author-email: psuaerofighter@gmail.com
Project-URL: Bug Tracker, https://github.com/Shai-Alit/viyapy/issues
Classifier: Programming Language :: Python :: 3
Classifier: License :: OSI Approved :: MIT License
Classifier: Operating System :: OS Independent
Requires-Python: >=3.6
License-File: LICENSE
